devshell/__init__.py
devshell/__main__.py
devshell/injector.py
devshell/ptcmd.py
devshell/shell.py
devshell-0.0.7.dist-info/LICENSE
devshell-0.0.7.dist-info/METADATA
devshell-0.0.7.dist-info/WHEEL
devshell-0.0.7.dist-info/top_level.txt
devshell-0.0.7.dist-info/RECORD
