Metadata-Version: 2.1
Name: devshell
Version: 0.0.7
Summary: Shell-like tool to make it easier to develop python code
Home-page: https://github.com/mmiguel6288code/devshell
Author: Matthew Miguel
Author-email: mmiguel6288code@gmail.com
Maintainer: Matthew Miguel
Maintainer-email: mmiguel6288code@gmail.com
License: MIT
Keywords: doctest,doctests,docstring,docstrings,tests,testing,test,shell,inspect,inspection,creating,create,run,running,interactive,coverage,pytest
Platform: UNKNOWN
Classifier: Intended Audience :: Developers
Classifier: License :: OSI Approved :: MIT License
Classifier: Natural Language :: English
Classifier: Operating System :: OS Independent
Classifier: Programming Language :: Python :: 2.7
Classifier: Programming Language :: Python :: 3.5
Classifier: Programming Language :: Python :: Implementation :: CPython
Requires-Dist: pypager
Requires-Dist: pytest
Requires-Dist: coverage
Requires-Dist: prompt-toolkit
Requires-Dist: pdoc3
